{
  "subject": "English",
  "topic": "Noun",
  "questions": [
    {
      "id": "00001",
      "question": "<b> MY NEW BICYCLE</b><br/> I got a new bicycle for my birthday. The best one in the shop. It's got gears to make it go faster And brakes so I can stop. There's a bell to ring on the handlebars So everyone, clear the way! I'm racing off on my bicycle Around the park today",
      "options": [
        
      ],
      "answers": [
        {
          "id": "001",
          "optionId": ""
        }
      ]
    },
	{
      "id": "00002",
      "question": "What did the poet get for his birthday?",
      "options": [
        {
          "id": "A",
          "option": "Gears"
        },
        {
          "id": "B",
          "option": "Bicycle"
        },
        {
          "id": "C",
          "option": "Bell"
        },
        {
          "id": "D",
          "option": "Handlebars"
        }
      ],
      "answers": [
        {
          "id": "001",
          "optionId": "B"
        }
      ]
    },
	{
      "id": "00003",
      "question": " Where is the bell on the bicycle?",
      "options": [
        {
          "id": "A",
          "option": " On the handlebars"
        },
        {
          "id": "B",
          "option": " On the spikes"
        },
        {
          "id": "C",
          "option": " On the brakes"
        },
        {
          "id": "D",
          "option": " On the wheels"
        }
      ],
      "answers": [
        {
          "id": "001",
          "optionId": "A"
        }
      ]
    },
	{
      "id": "00004",
      "question": " Where is the poet cycling?",
      "options": [
        {
          "id": "A",
          "option": " Around the shop"
        },
        {
          "id": "B",
          "option": " On the road to the park"
        },
        {
          "id": "C",
          "option": " Around the park"
        },
        {
          "id": "D",
          "option": " In the park"
        }
      ],
      "answers": [
        {
          "id": "001",
          "optionId": "C"
        }
      ]
    }
	
	
	
  ]
}